{
 "actions": [],
 "allow_rename": 1,
 "creation": "2026-02-18 00:37:03.793655",
 "doctype": "DocType",
 "editable_grid": 1,
 "engine": "InnoDB",
 "field_order": [
  "company",
  "period_type",
  "warranty_period"
 ],
 "fields": [
  {
   "fieldname": "company",
   "fieldtype": "Link",
   "in_list_view": 1,
   "label": "Company",
   "options": "Company",
   "reqd": 1
  },
  {
   "fieldname": "warranty_period",
   "fieldtype": "Float",
   "in_list_view": 1,
   "label": "Warranty Period",
   "reqd": 1
  },
  {
   "default": "Month",
   "fieldname": "period_type",
   "fieldtype": "Select",
   "in_list_view": 1,
   "label": "Period Type",
   "options": "Day\nMonth\nYear",
   "reqd": 1
  }
 ],
 "grid_page_length": 50,
 "index_web_pages_for_search": 1,
 "istable": 1,
 "links": [],
 "modified": "2026-02-18 00:42:13.997354",
 "modified_by": "Administrator",
 "module": "Management System",
 "name": "Item Warranty Period",
 "owner": "Administrator",
 "permissions": [],
 "row_format": "Dynamic",
 "rows_threshold_for_grid_search": 20,
 "sort_field": "modified",
 "sort_order": "DESC",
 "states": []
}